[
  {
    "inputs": [
      {
        "internalType": "contract IJBOperatorStore",
        "name": "_operatorStore",
        "type": "address"
      },
      {
        "internalType": "contract IJBProjects",
        "name": "_projects",
        "type": "address"
      },
      {
        "internalType": "contract IJBFundingCycleStore",
        "name": "_fundingCycleStore",
        "type": "address"
      },
      {
        "internalType": "address",
        "name": "_owner",
        "type": "address"
      }
    ],
    "stateMutability": "nonpayable",
    "type": "constructor"
  },
  {
    "inputs": [],
    "name": "DUPLICATE_TERMINALS",
    "type": "error"
  },
  {
    "inputs": [],
    "name": "INVALID_PROJECT_ID_IN_DIRECTORY",
    "type": "error"
  },
  {
    "inputs": [],
    "name": "SET_CONTROLLER_NOT_ALLOWED",
    "type": "error"
  },
  {
    "inputs": [],
    "name": "SET_TERMINALS_NOT_ALLOWED",
    "type": "error"
  },
  {
    "inputs": [],
    "name": "TOKEN_NOT_ACCEPTED",
    "type": "error"
  },
  {
    "inputs": [],
    "name": "UNAUTHORIZED",
    "type": "error"
  },
  {
    "anonymous": false,
    "inputs": [
      {
        "indexed": true,
        "internalType": "uint256",
        "name": "projectId",
        "type": "uint256"
      },
      {
        "indexed": true,
        "internalType": "contract IJBPaymentTerminal",
        "name": "terminal",
        "type": "address"
      },
      {
        "indexed": false,
        "internalType": "address",
        "name": "caller",
        "type": "address"
      }
    ],
    "name": "AddTerminal",
    "type": "event"
  },
  {
    "anonymous": false,
    "inputs": [
      {
        "indexed": true,
        "internalType": "address",
        "name": "previousOwner",
        "type": "address"
      },
      {
        "indexed": true,
        "internalType": "address",
        "name": "newOwner",
        "type": "address"
      }
    ],
    "name": "OwnershipTransferred",
    "type": "event"
  },
  {
    "anonymous": false,
    "inputs": [
      {
        "indexed": true,
        "internalType": "uint256",
        "name": "projectId",
        "type": "uint256"
      },
      {
        "indexed": true,
        "internalType": "address",
        "name": "controller",
        "type": "address"
      },
      {
        "indexed": false,
        "internalType": "address",
        "name": "caller",
        "type": "address"
      }
    ],
    "name": "SetController",
    "type": "event"
  },
  {
    "anonymous": false,
    "inputs": [
      {
        "indexed": true,
        "internalType": "address",
        "name": "addr",
        "type": "address"
      },
      {
        "indexed": true,
        "internalType": "bool",
        "name": "flag",
        "type": "bool"
      },
      {
        "indexed": false,
        "internalType": "address",
        "name": "caller",
        "type": "address"
      }
    ],
    "name": "SetIsAllowedToSetFirstController",
    "type": "event"
  },
  {
    "anonymous": false,
    "inputs": [
      {
        "indexed": true,
        "internalType": "uint256",
        "name": "projectId",
        "type": "uint256"
      },
      {
        "indexed": true,
        "internalType": "address",
        "name": "token",
        "type": "address"
      },
      {
        "indexed": true,
        "internalType": "contract IJBPaymentTerminal",
        "name": "terminal",
        "type": "address"
      },
      {
        "indexed": false,
        "internalType": "address",
        "name": "caller",
        "type": "address"
      }
    ],
    "name": "SetPrimaryTerminal",
    "type": "event"
  },
  {
    "anonymous": false,
    "inputs": [
      {
        "indexed": true,
        "internalType": "uint256",
        "name": "projectId",
        "type": "uint256"
      },
      {
        "indexed": false,
        "internalType": "contract IJBPaymentTerminal[]",
        "name": "terminals",
        "type": "address[]"
      },
      {
        "indexed": false,
        "internalType": "address",
        "name": "caller",
        "type": "address"
      }
    ],
    "name": "SetTerminals",
    "type": "event"
  },
  {
    "inputs": [
      {
        "internalType": "uint256",
        "name": "",
        "type": "uint256"
      }
    ],
    "name": "controllerOf",
    "outputs": [
      {
        "internalType": "address",
        "name": "",
        "type": "address"
      }
    ],
    "stateMutability": "view",
    "type": "function"
  },
  {
    "inputs": [],
    "name": "fundingCycleStore",
    "outputs": [
      {
        "internalType": "contract IJBFundingCycleStore",
        "name": "",
        "type": "address"
      }
    ],
    "stateMutability": "view",
    "type": "function"
  },
  {
    "inputs": [
      {
        "internalType": "address",
        "name": "",
        "type": "address"
      }
    ],
    "name": "isAllowedToSetFirstController",
    "outputs": [
      {
        "internalType": "bool",
        "name": "",
        "type": "bool"
      }
    ],
    "stateMutability": "view",
    "type": "function"
  },
  {
    "inputs": [
      {
        "internalType": "uint256",
        "name": "_projectId",
        "type": "uint256"
      },
      {
        "internalType": "contract IJBPaymentTerminal",
        "name": "_terminal",
        "type": "address"
      }
    ],
    "name": "isTerminalOf",
    "outputs": [
      {
        "internalType": "bool",
        "name": "",
        "type": "bool"
      }
    ],
    "stateMutability": "view",
    "type": "function"
  },
  {
    "inputs": [],
    "name": "operatorStore",
    "outputs": [
      {
        "internalType": "contract IJBOperatorStore",
        "name": "",
        "type": "address"
      }
    ],
    "stateMutability": "view",
    "type": "function"
  },
  {
    "inputs": [],
    "name": "owner",
    "outputs": [
      {
        "internalType": "address",
        "name": "",
        "type": "address"
      }
    ],
    "stateMutability": "view",
    "type": "function"
  },
  {
    "inputs": [
      {
        "internalType": "uint256",
        "name": "_projectId",
        "type": "uint256"
      },
      {
        "internalType": "address",
        "name": "_token",
        "type": "address"
      }
    ],
    "name": "primaryTerminalOf",
    "outputs": [
      {
        "internalType": "contract IJBPaymentTerminal",
        "name": "",
        "type": "address"
      }
    ],
    "stateMutability": "view",
    "type": "function"
  },
  {
    "inputs": [],
    "name": "projects",
    "outputs": [
      {
        "internalType": "contract IJBProjects",
        "name": "",
        "type": "address"
      }
    ],
    "stateMutability": "view",
    "type": "function"
  },
  {
    "inputs": [],
    "name": "renounceOwnership",
    "outputs": [],
    "stateMutability": "nonpayable",
    "type": "function"
  },
  {
    "inputs": [
      {
        "internalType": "uint256",
        "name": "_projectId",
        "type": "uint256"
      },
      {
        "internalType": "address",
        "name": "_controller",
        "type": "address"
      }
    ],
    "name": "setControllerOf",
    "outputs": [],
    "stateMutability": "nonpayable",
    "type": "function"
  },
  {
    "inputs": [
      {
        "internalType": "address",
        "name": "_address",
        "type": "address"
      },
      {
        "internalType": "bool",
        "name": "_flag",
        "type": "bool"
      }
    ],
    "name": "setIsAllowedToSetFirstController",
    "outputs": [],
    "stateMutability": "nonpayable",
    "type": "function"
  },
  {
    "inputs": [
      {
        "internalType": "uint256",
        "name": "_projectId",
        "type": "uint256"
      },
      {
        "internalType": "address",
        "name": "_token",
        "type": "address"
      },
      {
        "internalType": "contract IJBPaymentTerminal",
        "name": "_terminal",
        "type": "address"
      }
    ],
    "name": "setPrimaryTerminalOf",
    "outputs": [],
    "stateMutability": "nonpayable",
    "type": "function"
  },
  {
    "inputs": [
      {
        "internalType": "uint256",
        "name": "_projectId",
        "type": "uint256"
      },
      {
        "internalType": "contract IJBPaymentTerminal[]",
        "name": "_terminals",
        "type": "address[]"
      }
    ],
    "name": "setTerminalsOf",
    "outputs": [],
    "stateMutability": "nonpayable",
    "type": "function"
  },
  {
    "inputs": [
      {
        "internalType": "uint256",
        "name": "_projectId",
        "type": "uint256"
      }
    ],
    "name": "terminalsOf",
    "outputs": [
      {
        "internalType": "contract IJBPaymentTerminal[]",
        "name": "",
        "type": "address[]"
      }
    ],
    "stateMutability": "view",
    "type": "function"
  },
  {
    "inputs": [
      {
        "internalType": "address",
        "name": "newOwner",
        "type": "address"
      }
    ],
    "name": "transferOwnership",
    "outputs": [],
    "stateMutability": "nonpayable",
    "type": "function"
  }
]